aglite_test.core-0.7.0b20230314-py3.10-nspkg.pth
autogluon/core/__init__.py
autogluon/core/_setup_utils.py
autogluon/core/constants.py
autogluon/core/dataset.py
autogluon/core/space.py
autogluon/core/version.py
autogluon/core/augmentation/__init__.py
autogluon/core/augmentation/distill_utils.py
autogluon/core/calibrate/__init__.py
autogluon/core/calibrate/conformity_score.py
autogluon/core/calibrate/temperature_scaling.py
autogluon/core/data/__init__.py
autogluon/core/data/cleaner.py
autogluon/core/data/label_cleaner.py
autogluon/core/hpo/__init__.py
autogluon/core/hpo/constants.py
autogluon/core/hpo/exceptions.py
autogluon/core/hpo/executors.py
autogluon/core/hpo/ray_hpo.py
autogluon/core/hpo/ray_tune_constants.py
autogluon/core/hpo/ray_tune_scheduler.py
autogluon/core/hpo/ray_tune_scheduler_factory.py
autogluon/core/hpo/ray_tune_searcher_factory.py
autogluon/core/hpo/space_converter.py
autogluon/core/learner/__init__.py
autogluon/core/learner/abstract_learner.py
autogluon/core/metrics/__init__.py
autogluon/core/metrics/classification_metrics.py
autogluon/core/metrics/quantile_metrics.py
autogluon/core/metrics/softclass_metrics.py
autogluon/core/models/__init__.py
autogluon/core/models/_utils.py
autogluon/core/models/abstract/__init__.py
autogluon/core/models/abstract/_tags.py
autogluon/core/models/abstract/abstract_model.py
autogluon/core/models/abstract/abstract_nn_model.py
autogluon/core/models/abstract/model_trial.py
autogluon/core/models/dummy/__init__.py
autogluon/core/models/dummy/_dummy_quantile_regressor.py
autogluon/core/models/dummy/dummy_model.py
autogluon/core/models/ensemble/__init__.py
autogluon/core/models/ensemble/bagged_ensemble_model.py
autogluon/core/models/ensemble/fold_fitting_strategy.py
autogluon/core/models/ensemble/ray_parallel_fold_fitting_strategy.py
autogluon/core/models/ensemble/stacker_ensemble_model.py
autogluon/core/models/ensemble/weighted_ensemble_model.py
autogluon/core/models/greedy_ensemble/__init__.py
aglite_test.core-0.7.0b20230314.dist-info/LICENSE
aglite_test.core-0.7.0b20230314.dist-info/METADATA
aglite_test.core-0.7.0b20230314.dist-info/NOTICE
aglite_test.core-0.7.0b20230314.dist-info/WHEEL
aglite_test.core-0.7.0b20230314.dist-info/namespace_packages.txt
aglite_test.core-0.7.0b20230314.dist-info/top_level.txt
aglite_test.core-0.7.0b20230314.dist-info/zip-safe
aglite_test.core-0.7.0b20230314.dist-info/RECORD
