Metadata-Version: 2.1
Name: aglite-test.core
Version: 0.7.0b20230314
Summary: AutoML for Image, Text, and Tabular Data
Home-page: https://github.com/autogluon/autogluon
Author: AutoGluon Community
License: Apache-2.0
Project-URL: Documentation, https://auto.gluon.ai
Project-URL: Bug Reports, https://github.com/autogluon/autogluon/issues
Project-URL: Source, https://github.com/autogluon/autogluon/
Project-URL: Contribute!, https://github.com/autogluon/autogluon/blob/master/CONTRIBUTING.md
Classifier: Development Status :: 4 - Beta
Classifier: Intended Audience :: Education
Classifier: Intended Audience :: Developers
Classifier: Intended Audience :: Science/Research
Classifier: Intended Audience :: Customer Service
Classifier: Intended Audience :: Financial and Insurance Industry
Classifier: Intended Audience :: Healthcare Industry
Classifier: Intended Audience :: Telecommunications Industry
Classifier: License :: OSI Approved :: Apache Software License
Classifier: Operating System :: MacOS
Classifier: Operating System :: Microsoft :: Windows
Classifier: Operating System :: POSIX
Classifier: Operating System :: Unix
Classifier: Programming Language :: Python :: 3
Classifier: Programming Language :: Python :: 3.8
Classifier: Programming Language :: Python :: 3.9
Classifier: Programming Language :: Python :: 3.10
Classifier: Topic :: Software Development
Classifier: Topic :: Scientific/Engineering :: Artificial Intelligence
Classifier: Topic :: Scientific/Engineering :: Information Analysis
Classifier: Topic :: Scientific/Engineering :: Image Recognition
Requires-Python: >=3.8, <3.11
License-File: ../LICENSE
License-File: ../NOTICE
Requires-Dist: numpy (<1.27,>=1.21)
Requires-Dist: scipy (<1.12,>=1.5.4)
Requires-Dist: scikit-learn (<1.3,>=1.0)
Requires-Dist: pandas (<1.6,>=1.4.1)
Requires-Dist: tqdm (<5,>=4.38)
Requires-Dist: matplotlib
Requires-Dist: aglite-test.common (==0.7.0b20230314)
Provides-Extra: all
Requires-Dist: ray (<2.3,>=2.2) ; extra == 'all'
Requires-Dist: ray[tune] (<2.3,>=2.2) ; extra == 'all'
Requires-Dist: hyperopt (<0.2.8,>=0.2.7) ; extra == 'all'
Provides-Extra: ray
Requires-Dist: ray (<2.3,>=2.2) ; extra == 'ray'
Provides-Extra: raytune
Requires-Dist: ray[tune] (<2.3,>=2.2) ; extra == 'raytune'
Requires-Dist: hyperopt (<0.2.8,>=0.2.7) ; extra == 'raytune'
Provides-Extra: tests
Requires-Dist: pytest-mypy ; extra == 'tests'
Requires-Dist: types-requests ; extra == 'tests'
Requires-Dist: pytest ; extra == 'tests'
Requires-Dist: types-setuptools ; extra == 'tests'
